django_makeallmessages/__init__.py
django_makeallmessages/settings.py
django_makeallmessages/management/__init__.py
django_makeallmessages/management/commands/__init__.py
django_makeallmessages/management/commands/makeallmessages.py
django_makeallmessages-0.2.1.dist-info/LICENSE
django_makeallmessages-0.2.1.dist-info/METADATA
django_makeallmessages-0.2.1.dist-info/WHEEL
django_makeallmessages-0.2.1.dist-info/top_level.txt
django_makeallmessages-0.2.1.dist-info/RECORD
