Metadata-Version: 2.1
Name: django-makeallmessages
Version: 0.2.1
Summary: Django Makeallmessages is a tool designed to ease the message making in your Django project.
Home-page: https://github.com/vonNiklasson/django-makeallmessages
Author: Johan Niklasson
Author-email: johan@niklasson.me
License: UNKNOWN
Platform: UNKNOWN
Classifier: Environment :: Web Environment
Classifier: Framework :: Django
Classifier: Framework :: Django :: 2.2
Classifier: Framework :: Django :: 3.0
Classifier: Framework :: Django :: 3.1
Classifier: Intended Audience :: Developers
Classifier: License :: OSI Approved :: MIT License
Classifier: Programming Language :: Python :: 3.5
Classifier: Programming Language :: Python :: 3.6
Classifier: Programming Language :: Python :: 3.7
Classifier: Programming Language :: Python :: 3.8
Classifier: Programming Language :: Python :: 3.9
Classifier: License :: OSI Approved :: MIT License
Classifier: Operating System :: OS Independent
Classifier: Topic :: Utilities
Requires-Python: >=3.5
